__init__.py
psycop_ml_utils/utils.py
psycop_ml_utils/utils_for_testing.py
psycop_ml_utils/loaders/synth/raw/load_synth_data.py
psycop_ml_utils/sql/__init__.py
psycop_ml_utils/sql/loader.py
psycop_ml_utils/sql/writer.py
psycop_ml_utils/synth_data_generator/__init__.py
psycop_ml_utils/synth_data_generator/synth_col_generators.py
psycop_ml_utils/synth_data_generator/synth_prediction_times_generator.py
psycop_ml_utils/synth_data_generator/synth_txt_data_generator.py
psycop_ml_utils/synth_data_generator/utils.py
psycop_ml_utils/wandb/wandb_try_except_decorator.py
psycopmlutils-0.11.0.dist-info/METADATA
psycopmlutils-0.11.0.dist-info/WHEEL
psycopmlutils-0.11.0.dist-info/top_level.txt
psycopmlutils-0.11.0.dist-info/RECORD
