Metadata-Version: 2.1
Name: psycopmlutils
Version: 0.11.0
Summary: A collection of machine-learning utilities used across the psycop-projects.
Author: Kenneth Enevoldsen
Author-email: Martin Bernstorff <martinbernstorff@gmail.com>, Lasse Hansen <lasseh0310@gmail.com>
Classifier: Environment :: Console
Classifier: Intended Audience :: Developers
Classifier: Intended Audience :: Science/Research
Classifier: Topic :: Scientific/Engineering
Classifier: Topic :: Scientific/Engineering :: Artificial Intelligence
Classifier: Operating System :: POSIX :: Linux
Classifier: Operating System :: MacOS :: MacOS X
Classifier: Operating System :: Microsoft :: Windows
Classifier: Programming Language :: Python :: 3.9
Requires-Python: >=3.8.0
Requires-Dist: pydantic (>=1.9.0)
Requires-Dist: numpy (<1.25.0,>=1.23.3)
Requires-Dist: scipy (<1.11.0,>=1.8.1)
Requires-Dist: pandas (<1.6.0,>=1.4.4)
Requires-Dist: catalogue (<2.1.0,>=2.0.8)
Requires-Dist: wasabi (<1.2.0,>=0.9.0)
Requires-Dist: scikit-learn (<1.3.0,>=1.1.2)
Requires-Dist: srsly (<2.5.0,>=2.4.4)
Requires-Dist: wandb (<0.13.11,>=0.12.7)
Requires-Dist: psutil (<6.0.0,>=5.9.1)
Requires-Dist: dill (<0.3.7,>=0.3.5)
Requires-Dist: SQLAlchemy (<2.0.5,>=1.4.40)
Requires-Dist: pyodbc (<=4.1.0,>=4.0.34)
Requires-Dist: transformers (<4.27.0,>=4.22.0)
Provides-Extra: dev
Requires-Dist: black (>=22.12.0) ; extra == 'dev'
Requires-Dist: pytest (>=7.2.0) ; extra == 'dev'
Requires-Dist: pytest-cov (>=4.0.0) ; extra == 'dev'
Requires-Dist: Sphinx (>=5.3.0) ; extra == 'dev'
Requires-Dist: furo (<2022.12.8,>=2022.6.4) ; extra == 'dev'
Requires-Dist: sphinx-copybutton (>=0.5.0) ; extra == 'dev'
Requires-Dist: sphinxext-opengraph (>=0.7.0) ; extra == 'dev'
Requires-Dist: myst-parser (>=0.18.0) ; extra == 'dev'
Requires-Dist: flake8 (>=6.0.0) ; extra == 'dev'
Requires-Dist: docformatter (<1.5.2,>=1.4.0) ; extra == 'dev'
Requires-Dist: mypy (<1.1,>=0.971) ; extra == 'dev'
Requires-Dist: pytest-xdist (>=3.0.2) ; extra == 'dev'
Requires-Dist: pre-commit (<3.2.0,>=2.20.0) ; extra == 'dev'
